grapho/__init__.py
grapho/digraph.py
grapho/graph.py
grapho-0.1.0.dist-info/AUTHORS.rst
grapho-0.1.0.dist-info/LICENSE
grapho-0.1.0.dist-info/METADATA
grapho-0.1.0.dist-info/WHEEL
grapho-0.1.0.dist-info/top_level.txt
grapho-0.1.0.dist-info/RECORD
